resnest/__init__.py
resnest/transforms.py
resnest/utils.py
resnest/version.py
resnest/gluon/__init__.py
resnest/gluon/ablation.py
resnest/gluon/data_utils.py
resnest/gluon/dropblock.py
resnest/gluon/model_store.py
resnest/gluon/model_zoo.py
resnest/gluon/resnest.py
resnest/gluon/resnet.py
resnest/gluon/splat.py
resnest/torch/__init__.py
resnest/torch/ablation.py
resnest/torch/resnest.py
resnest/torch/resnet.py
resnest/torch/splat.py
resnest-0.0.5.dist-info/LICENSE
resnest-0.0.5.dist-info/METADATA
resnest-0.0.5.dist-info/WHEEL
resnest-0.0.5.dist-info/top_level.txt
resnest-0.0.5.dist-info/RECORD
